MANIFEST.in
README.rst
setup.py
flatpages/__init__.py
flatpages/bootstrap.py
flatpages/helpers.py
flatpages/partials.py
flatpages/controllers/__init__.py
flatpages/controllers/root.py
flatpages/lib/__init__.py
flatpages/lib/formatters.py
flatpages/lib/widgets.py
flatpages/model/__init__.py
flatpages/model/ming.py
flatpages/model/sqla.py
flatpages/public/__init__.py
flatpages/public/jquery.js
flatpages/public/markitup/jquery.markitup.js
flatpages/public/markitup/sets/html/set.js
flatpages/public/markitup/sets/html/style.css
flatpages/public/markitup/sets/html/images/bold.png
flatpages/public/markitup/sets/html/images/clean.png
flatpages/public/markitup/sets/html/images/image.png
flatpages/public/markitup/sets/html/images/italic.png
flatpages/public/markitup/sets/html/images/link.png
flatpages/public/markitup/sets/html/images/list-bullet.png
flatpages/public/markitup/sets/html/images/list-numeric.png
flatpages/public/markitup/sets/html/images/picture.png
flatpages/public/markitup/sets/html/images/preview.png
flatpages/public/markitup/sets/html/images/stroke.png
flatpages/public/markitup/sets/rst/readme.txt
flatpages/public/markitup/sets/rst/set.js
flatpages/public/markitup/sets/rst/style.css
flatpages/public/markitup/sets/rst/images/bg-editor-rst.png
flatpages/public/markitup/sets/rst/images/bold.png
flatpages/public/markitup/sets/rst/images/code.png
flatpages/public/markitup/sets/rst/images/h1.png
flatpages/public/markitup/sets/rst/images/h2.png
flatpages/public/markitup/sets/rst/images/h3.png
flatpages/public/markitup/sets/rst/images/italic.png
flatpages/public/markitup/sets/rst/images/link.png
flatpages/public/markitup/sets/rst/images/list-bullet.png
flatpages/public/markitup/sets/rst/images/list-numeric.png
flatpages/public/markitup/sets/rst/images/picture.png
flatpages/public/markitup/sets/rst/images/preview.png
flatpages/public/markitup/sets/rst/images/quotes.png
flatpages/public/markitup/skins/markitup/style.css
tgapp_flatpages.egg-info/PKG-INFO
tgapp_flatpages.egg-info/SOURCES.txt
tgapp_flatpages.egg-info/dependency_links.txt
tgapp_flatpages.egg-info/entry_points.txt
tgapp_flatpages.egg-info/not-zip-safe
tgapp_flatpages.egg-info/requires.txt
tgapp_flatpages.egg-info/top_level.txt