Metadata-Version: 1.0
Name: tgapp-flatpages
Version: 0.3.3
Summary: Pluggable application to manage static pages (/about) on DB (sqlalchemy or ming) with RST or HTML
Home-page: https://github.com/axant/tgapp-flatpages
Author: Alessandro Molina
Author-email: alessandro.molina@axant.it
License: UNKNOWN
Keywords: turbogears2.application
Platform: UNKNOWN
